colortruck/__init__.py
colortruck/colortruck.py
colortruck-0.1.0.dist-info/METADATA
colortruck-0.1.0.dist-info/WHEEL
colortruck-0.1.0.dist-info/top_level.txt
colortruck-0.1.0.dist-info/RECORD
